odoo_isabel_connect/__init__.c
odoo_isabel_connect/__init__.cpython-312-x86_64-linux-gnu.so
odoo_isabel_connect/__init__.cpython-314-x86_64-linux-musl.so
odoo_isabel_connect/__init__.py
odoo_isabel_connect/constants.c
odoo_isabel_connect/constants.cpython-312-x86_64-linux-gnu.so
odoo_isabel_connect/constants.cpython-314-x86_64-linux-musl.so
odoo_isabel_connect/constants.py
odoo_isabel_connect/odoo_certificate_key_isabel_connect.c
odoo_isabel_connect/odoo_certificate_key_isabel_connect.cpython-312-x86_64-linux-gnu.so
odoo_isabel_connect/odoo_certificate_key_isabel_connect.cpython-314-x86_64-linux-musl.so
odoo_isabel_connect/odoo_certificate_key_isabel_connect.py
odoo_isabel_connect/odoo_isabel_connect_pain.c
odoo_isabel_connect/odoo_isabel_connect_pain.cpython-312-x86_64-linux-gnu.so
odoo_isabel_connect/odoo_isabel_connect_pain.cpython-314-x86_64-linux-musl.so
odoo_isabel_connect/odoo_isabel_connect_pain.py
odoo_isabel_connect/odoo_isabel_connect_user.c
odoo_isabel_connect/odoo_isabel_connect_user.cpython-312-x86_64-linux-gnu.so
odoo_isabel_connect/odoo_isabel_connect_user.cpython-314-x86_64-linux-musl.so
odoo_isabel_connect/odoo_isabel_connect_user.py
odoo_isabel_connect-1.0.1.dist-info/METADATA
odoo_isabel_connect-1.0.1.dist-info/WHEEL
odoo_isabel_connect-1.0.1.dist-info/top_level.txt
odoo_isabel_connect-1.0.1.dist-info/RECORD
odoo_isabel_connect-1.0.1.dist-info/licenses/LICENSE
